interaktiv.id4me-1.1.1-py2.7-nspkg.pth
interaktiv/id4me/__init__.py
interaktiv/id4me/functions.py
interaktiv/id4me/testing.py
interaktiv/id4me/controlpanel/__init__.py
interaktiv/id4me/controlpanel/id4me.py
interaktiv/id4me/registry/__init__.py
interaktiv/id4me/registry/id4me.py
interaktiv/id4me/tests/__init__.py
interaktiv/id4me/utilities/__init__.py
interaktiv/id4me/utilities/authentication.py
interaktiv/id4me/views/__init__.py
interaktiv/id4me/views/authenticate.py
interaktiv/id4me/views/controlpanel.py
interaktiv/id4me/views/validate.py
interaktiv.id4me-1.1.1.dist-info/METADATA
interaktiv.id4me-1.1.1.dist-info/WHEEL
interaktiv.id4me-1.1.1.dist-info/entry_points.txt
interaktiv.id4me-1.1.1.dist-info/namespace_packages.txt
interaktiv.id4me-1.1.1.dist-info/top_level.txt
interaktiv.id4me-1.1.1.dist-info/RECORD
