Metadata-Version: 2.1
Name: interaktiv.id4me
Version: 1.1.1
Summary: ID4Me Plugin for Plone 5.x
Home-page: https://github.com/interaktivgmbh/interaktiv.id4me
Author: Thomas Kastenholz
Author-email: kastenholz@interaktiv.de
License: GPL version 2
Platform: UNKNOWN
Classifier: Environment :: Web Environment
Classifier: Framework :: Plone
Classifier: Framework :: Plone :: 5.1
Classifier: Operating System :: OS Independent
Classifier: Programming Language :: Python
Classifier: Programming Language :: Python :: 2.7
Classifier: Topic :: Software Development :: Libraries :: Python Modules
Requires-Dist: setuptools
Requires-Dist: unittest2
Requires-Dist: plone.testing
Requires-Dist: plone.app.testing
Requires-Dist: Products.BeakerSessionDataManager
Requires-Dist: id4me-rp-client
Provides-Extra: test
Requires-Dist: plone.app.testing; extra == 'test'
